{
  "SetViewMode": "55",
  "last_update": "2026-02-04 04:09:20",
  "items": [
    {
      "title": "[COLOR cyan][04/02 14:00][/COLOR] [COLOR gold]Legia Warszawa U19 vs Ajax U19[/COLOR] - [COLOR lime]Sky Sport Austria 1[/COLOR] [COLOR orange][at][/COLOR] [COLOR yellow]Link 1[/COLOR]",
      "myresolve": "sansat@@16@@AT",
      "thumbnail": "https://cdn-icons-png.flaticon.com/512/3524/3524659.png",
      "fanart": "https://www.stadiotardini.it/wp-content/uploads/2016/12/mandrakata.jpg",
      "info": "04-Feb 14:00 | Europe UEFA Youth League | Football | Lang: AT"
    },
    {
      "title": "[COLOR cyan][04/02 14:00][/COLOR] [COLOR gold]Legia Warszawa U19 vs Ajax U19[/COLOR] - [COLOR lime]Sky Sport Austria 1[/COLOR] [COLOR orange][at][/COLOR] [COLOR yellow]Link 2[/COLOR]",
      "myresolve": "sansat@@16@@AT",
      "thumbnail": "https://cdn-icons-png.flaticon.com/512/3524/3524659.png",
      "fanart": "https://www.stadiotardini.it/wp-content/uploads/2016/12/mandrakata.jpg",
      "info": "04-Feb 14:00 | Europe UEFA Youth League | Football | Lang: AT"
    },
    {
      "title": "[COLOR cyan][04/02 16:00][/COLOR] [COLOR gold]HJK U19 vs Manchester City U19[/COLOR] - [COLOR lime]M. Liga de Campeones 3[/COLOR] [COLOR orange][es][/COLOR] [COLOR yellow]Link 1[/COLOR]",
      "myresolve": "sansat@@28@@ES",
      "thumbnail": "https://cdn-icons-png.flaticon.com/512/3524/3524659.png",
      "fanart": "https://www.stadiotardini.it/wp-content/uploads/2016/12/mandrakata.jpg",
      "info": "04-Feb 16:00 | Europe UEFA Youth League | Football | Lang: ES"
    },
    {
      "title": "[COLOR cyan][04/02 16:00][/COLOR] [COLOR gold]HJK U19 vs Manchester City U19[/COLOR] - [COLOR lime]M. Liga de Campeones 3[/COLOR] [COLOR orange][es][/COLOR] [COLOR yellow]Link 2[/COLOR]",
      "myresolve": "sansat@@28@@ES",
      "thumbnail": "https://cdn-icons-png.flaticon.com/512/3524/3524659.png",
      "fanart": "https://www.stadiotardini.it/wp-content/uploads/2016/12/mandrakata.jpg",
      "info": "04-Feb 16:00 | Europe UEFA Youth League | Football | Lang: ES"
    },
    {
      "title": "[COLOR cyan][04/02 16:00][/COLOR] [COLOR gold]Benfica U19 vs Slavia Prague U19[/COLOR] - [COLOR lime]Nova Sport 4[/COLOR] [COLOR orange][cz][/COLOR] [COLOR yellow]Link 1[/COLOR]",
      "myresolve": "sansat@@44@@CZ",
      "thumbnail": "https://cdn-icons-png.flaticon.com/512/3524/3524659.png",
      "fanart": "https://www.stadiotardini.it/wp-content/uploads/2016/12/mandrakata.jpg",
      "info": "04-Feb 16:00 | Europe UEFA Youth League | Football | Lang: CZ"
    },
    {
      "title": "[COLOR cyan][04/02 16:00][/COLOR] [COLOR gold]Benfica U19 vs Slavia Prague U19[/COLOR] - [COLOR lime]Nova Sport 4[/COLOR] [COLOR orange][cz][/COLOR] [COLOR yellow]Link 2[/COLOR]",
      "myresolve": "sansat@@44@@CZ",
      "thumbnail": "https://cdn-icons-png.flaticon.com/512/3524/3524659.png",
      "fanart": "https://www.stadiotardini.it/wp-content/uploads/2016/12/mandrakata.jpg",
      "info": "04-Feb 16:00 | Europe UEFA Youth League | Football | Lang: CZ"
    },
    {
      "title": "[COLOR cyan][04/02 18:00][/COLOR] [COLOR gold]Real Betis U19 vs Tottenham Hotspur U19[/COLOR] - [COLOR lime]TNT Sports 4[/COLOR] [COLOR orange][gb][/COLOR] [COLOR yellow]Link 1[/COLOR]",
      "myresolve": "sansat@@4@@GB",
      "thumbnail": "https://cdn-icons-png.flaticon.com/512/3524/3524659.png",
      "fanart": "https://www.stadiotardini.it/wp-content/uploads/2016/12/mandrakata.jpg",
      "info": "04-Feb 18:00 | Europe UEFA Youth League | Football | Lang: GB"
    },
    {
      "title": "[COLOR cyan][04/02 18:00][/COLOR] [COLOR gold]Real Betis U19 vs Tottenham Hotspur U19[/COLOR] - [COLOR lime]TNT Sports 4[/COLOR] [COLOR orange][gb][/COLOR] [COLOR yellow]Link 2[/COLOR]",
      "myresolve": "sansat@@4@@GB",
      "thumbnail": "https://cdn-icons-png.flaticon.com/512/3524/3524659.png",
      "fanart": "https://www.stadiotardini.it/wp-content/uploads/2016/12/mandrakata.jpg",
      "info": "04-Feb 18:00 | Europe UEFA Youth League | Football | Lang: GB"
    },
    {
      "title": "[COLOR cyan][04/02 18:00][/COLOR] [COLOR gold]Real Betis U19 vs Tottenham Hotspur U19[/COLOR] - [COLOR lime]M. Liga de Campeones 2[/COLOR] [COLOR orange][es][/COLOR] [COLOR yellow]Link 1[/COLOR]",
      "myresolve": "sansat@@29@@ES",
      "thumbnail": "https://cdn-icons-png.flaticon.com/512/3524/3524659.png",
      "fanart": "https://www.stadiotardini.it/wp-content/uploads/2016/12/mandrakata.jpg",
      "info": "04-Feb 18:00 | Europe UEFA Youth League | Football | Lang: ES"
    },
    {
      "title": "[COLOR cyan][04/02 18:00][/COLOR] [COLOR gold]Real Betis U19 vs Tottenham Hotspur U19[/COLOR] - [COLOR lime]M. Liga de Campeones 2[/COLOR] [COLOR orange][es][/COLOR] [COLOR yellow]Link 2[/COLOR]",
      "myresolve": "sansat@@29@@ES",
      "thumbnail": "https://cdn-icons-png.flaticon.com/512/3524/3524659.png",
      "fanart": "https://www.stadiotardini.it/wp-content/uploads/2016/12/mandrakata.jpg",
      "info": "04-Feb 18:00 | Europe UEFA Youth League | Football | Lang: ES"
    },
    {
      "title": "[COLOR cyan][04/02 18:00][/COLOR] [COLOR gold]Koln U19 vs Inter U19[/COLOR] - [COLOR lime]DAZN1[/COLOR] [COLOR orange][de][/COLOR] [COLOR yellow]Link 1[/COLOR]",
      "myresolve": "sansat@@17@@DE",
      "thumbnail": "https://upload.wikimedia.org/wikipedia/commons/thumb/4/49/DAZN_1.svg/512px-DAZN_1.svg.png",
      "fanart": "https://static.vecteezy.com/system/resources/previews/041/446/736/non_2x/italy-national-flag-free-png.png",
      "info": "04-Feb 18:00 | Europe UEFA Youth League | Football | Lang: DE"
    },
    {
      "title": "[COLOR cyan][04/02 18:00][/COLOR] [COLOR gold]Koln U19 vs Inter U19[/COLOR] - [COLOR lime]DAZN1[/COLOR] [COLOR orange][de][/COLOR] [COLOR yellow]Link 2[/COLOR]",
      "myresolve": "sansat@@17@@DE",
      "thumbnail": "https://upload.wikimedia.org/wikipedia/commons/thumb/4/49/DAZN_1.svg/512px-DAZN_1.svg.png",
      "fanart": "https://static.vecteezy.com/system/resources/previews/041/446/736/non_2x/italy-national-flag-free-png.png",
      "info": "04-Feb 18:00 | Europe UEFA Youth League | Football | Lang: DE"
    },
    {
      "title": "[COLOR cyan][04/02 18:00][/COLOR] [COLOR gold]Koln U19 vs Inter U19[/COLOR] - [COLOR lime]M. Liga de Campeones 3[/COLOR] [COLOR orange][es][/COLOR] [COLOR yellow]Link 1[/COLOR]",
      "myresolve": "sansat@@28@@ES",
      "thumbnail": "https://cdn-icons-png.flaticon.com/512/3524/3524659.png",
      "fanart": "https://www.stadiotardini.it/wp-content/uploads/2016/12/mandrakata.jpg",
      "info": "04-Feb 18:00 | Europe UEFA Youth League | Football | Lang: ES"
    },
    {
      "title": "[COLOR cyan][04/02 18:00][/COLOR] [COLOR gold]Koln U19 vs Inter U19[/COLOR] - [COLOR lime]M. Liga de Campeones 3[/COLOR] [COLOR orange][es][/COLOR] [COLOR yellow]Link 2[/COLOR]",
      "myresolve": "sansat@@28@@ES",
      "thumbnail": "https://cdn-icons-png.flaticon.com/512/3524/3524659.png",
      "fanart": "https://www.stadiotardini.it/wp-content/uploads/2016/12/mandrakata.jpg",
      "info": "04-Feb 18:00 | Europe UEFA Youth League | Football | Lang: ES"
    }
  ]
}