{
  "SetViewMode": "55",
  "last_update": "2026-02-16 10:45:04",
  "items": [
    {
      "title": "[COLOR cyan][16/02 20:30][/COLOR] [COLOR gold]Macclesfield vs Brentford[/COLOR] - [COLOR lime]TNT Sports 1[/COLOR] [COLOR orange][gb][/COLOR] [COLOR yellow]Link 1[/COLOR]",
      "myresolve": "sansat@@1@@GB",
      "thumbnail": "https://cdn-icons-png.flaticon.com/512/3524/3524659.png",
      "fanart": "https://www.stadiotardini.it/wp-content/uploads/2016/12/mandrakata.jpg",
      "info": "16-Feb 20:30 | England FA Cup | Football | Lang: GB"
    },
    {
      "title": "[COLOR cyan][16/02 20:30][/COLOR] [COLOR gold]Macclesfield vs Brentford[/COLOR] - [COLOR lime]TNT Sports 1[/COLOR] [COLOR orange][gb][/COLOR] [COLOR yellow]Link 2[/COLOR]",
      "myresolve": "sansat@@1@@GB",
      "thumbnail": "https://cdn-icons-png.flaticon.com/512/3524/3524659.png",
      "fanart": "https://www.stadiotardini.it/wp-content/uploads/2016/12/mandrakata.jpg",
      "info": "16-Feb 20:30 | England FA Cup | Football | Lang: GB"
    },
    {
      "title": "[COLOR cyan][16/02 20:30][/COLOR] [COLOR gold]Macclesfield vs Brentford[/COLOR] - [COLOR lime]DAZN2[/COLOR] [COLOR orange][de][/COLOR] [COLOR yellow]Link 1[/COLOR]",
      "myresolve": "sansat@@18@@DE",
      "thumbnail": "https://3038.images-vfp2.ott.kaltura.com/Service.svc/GetImage/p/3038/entry_id/8395aa532bfc4e01b91098ff5bcd18d0/version/1",
      "fanart": "https://vectorflags.s3.amazonaws.com/flags/pt-circle-01.png",
      "info": "16-Feb 20:30 | England FA Cup | Football | Lang: DE"
    },
    {
      "title": "[COLOR cyan][16/02 20:30][/COLOR] [COLOR gold]Macclesfield vs Brentford[/COLOR] - [COLOR lime]DAZN2[/COLOR] [COLOR orange][de][/COLOR] [COLOR yellow]Link 2[/COLOR]",
      "myresolve": "sansat@@18@@DE",
      "thumbnail": "https://3038.images-vfp2.ott.kaltura.com/Service.svc/GetImage/p/3038/entry_id/8395aa532bfc4e01b91098ff5bcd18d0/version/1",
      "fanart": "https://vectorflags.s3.amazonaws.com/flags/pt-circle-01.png",
      "info": "16-Feb 20:30 | England FA Cup | Football | Lang: DE"
    },
    {
      "title": "[COLOR cyan][16/02 20:30][/COLOR] [COLOR gold]Macclesfield vs Brentford[/COLOR] - [COLOR lime]Sportsnet World[/COLOR] [COLOR orange][ca][/COLOR] [COLOR yellow]Link 1[/COLOR]",
      "myresolve": "sansat@@31@@CA",
      "thumbnail": "https://cdn-icons-png.flaticon.com/512/3524/3524659.png",
      "fanart": "https://www.stadiotardini.it/wp-content/uploads/2016/12/mandrakata.jpg",
      "info": "16-Feb 20:30 | England FA Cup | Football | Lang: CA"
    },
    {
      "title": "[COLOR cyan][16/02 20:30][/COLOR] [COLOR gold]Macclesfield vs Brentford[/COLOR] - [COLOR lime]Sportsnet World[/COLOR] [COLOR orange][ca][/COLOR] [COLOR yellow]Link 2[/COLOR]",
      "myresolve": "sansat@@31@@CA",
      "thumbnail": "https://cdn-icons-png.flaticon.com/512/3524/3524659.png",
      "fanart": "https://www.stadiotardini.it/wp-content/uploads/2016/12/mandrakata.jpg",
      "info": "16-Feb 20:30 | England FA Cup | Football | Lang: CA"
    },
    {
      "title": "[COLOR cyan][16/02 20:30][/COLOR] [COLOR gold]Macclesfield vs Brentford[/COLOR] - [COLOR lime]FOX One[/COLOR] [COLOR orange][mx][/COLOR] [COLOR yellow]Link 1[/COLOR]",
      "myresolve": "sansat@@85@@MX",
      "thumbnail": "https://cdn-icons-png.flaticon.com/512/3524/3524659.png",
      "fanart": "https://www.stadiotardini.it/wp-content/uploads/2016/12/mandrakata.jpg",
      "info": "16-Feb 20:30 | England FA Cup | Football | Lang: MX"
    },
    {
      "title": "[COLOR cyan][16/02 20:30][/COLOR] [COLOR gold]Macclesfield vs Brentford[/COLOR] - [COLOR lime]FOX One[/COLOR] [COLOR orange][mx][/COLOR] [COLOR yellow]Link 2[/COLOR]",
      "myresolve": "sansat@@85@@MX",
      "thumbnail": "https://cdn-icons-png.flaticon.com/512/3524/3524659.png",
      "fanart": "https://www.stadiotardini.it/wp-content/uploads/2016/12/mandrakata.jpg",
      "info": "16-Feb 20:30 | England FA Cup | Football | Lang: MX"
    },
    {
      "title": "[COLOR cyan][16/02 21:00][/COLOR] [COLOR gold]Coventry City vs Middlesbrough[/COLOR] - [COLOR lime]Sky Sports Football[/COLOR] [COLOR orange][gb][/COLOR] [COLOR yellow]Link 1[/COLOR]",
      "myresolve": "sansat@@4@@GB",
      "thumbnail": "https://cdn-icons-png.flaticon.com/512/3524/3524659.png",
      "fanart": "https://www.stadiotardini.it/wp-content/uploads/2016/12/mandrakata.jpg",
      "info": "16-Feb 21:00 | England Championship | Football | Lang: GB"
    },
    {
      "title": "[COLOR cyan][16/02 21:00][/COLOR] [COLOR gold]Coventry City vs Middlesbrough[/COLOR] - [COLOR lime]Sky Sports Football[/COLOR] [COLOR orange][gb][/COLOR] [COLOR yellow]Link 2[/COLOR]",
      "myresolve": "sansat@@4@@GB",
      "thumbnail": "https://cdn-icons-png.flaticon.com/512/3524/3524659.png",
      "fanart": "https://www.stadiotardini.it/wp-content/uploads/2016/12/mandrakata.jpg",
      "info": "16-Feb 21:00 | England Championship | Football | Lang: GB"
    },
    {
      "title": "[COLOR cyan][16/02 21:00][/COLOR] [COLOR gold]Coventry City vs Middlesbrough[/COLOR] - [COLOR lime]CBS Sports Network[/COLOR] [COLOR orange][us][/COLOR] [COLOR yellow]Link 1[/COLOR]",
      "myresolve": "sansat@@8@@US",
      "thumbnail": "https://cdn-icons-png.flaticon.com/512/3524/3524659.png",
      "fanart": "https://www.stadiotardini.it/wp-content/uploads/2016/12/mandrakata.jpg",
      "info": "16-Feb 21:00 | England Championship | Football | Lang: US"
    },
    {
      "title": "[COLOR cyan][16/02 21:00][/COLOR] [COLOR gold]Coventry City vs Middlesbrough[/COLOR] - [COLOR lime]CBS Sports Network[/COLOR] [COLOR orange][us][/COLOR] [COLOR yellow]Link 2[/COLOR]",
      "myresolve": "sansat@@8@@US",
      "thumbnail": "https://cdn-icons-png.flaticon.com/512/3524/3524659.png",
      "fanart": "https://www.stadiotardini.it/wp-content/uploads/2016/12/mandrakata.jpg",
      "info": "16-Feb 21:00 | England Championship | Football | Lang: US"
    },
    {
      "title": "[COLOR cyan][17/02 20:45][/COLOR] [COLOR gold]Charlton Athletic vs Portsmouth[/COLOR] - [COLOR lime]Sky Sports+[/COLOR] [COLOR orange][gb][/COLOR] [COLOR yellow]Link 1[/COLOR]",
      "myresolve": "sansat@@31@@GB",
      "thumbnail": "https://cdn-icons-png.flaticon.com/512/3524/3524659.png",
      "fanart": "https://www.stadiotardini.it/wp-content/uploads/2016/12/mandrakata.jpg",
      "info": "17-Feb 20:45 | England Championship | Football | Lang: GB"
    },
    {
      "title": "[COLOR cyan][17/02 20:45][/COLOR] [COLOR gold]Charlton Athletic vs Portsmouth[/COLOR] - [COLOR lime]Sky Sports+[/COLOR] [COLOR orange][gb][/COLOR] [COLOR yellow]Link 2[/COLOR]",
      "myresolve": "sansat@@31@@GB",
      "thumbnail": "https://cdn-icons-png.flaticon.com/512/3524/3524659.png",
      "fanart": "https://www.stadiotardini.it/wp-content/uploads/2016/12/mandrakata.jpg",
      "info": "17-Feb 20:45 | England Championship | Football | Lang: GB"
    },
    {
      "title": "[COLOR cyan][17/02 20:45][/COLOR] [COLOR gold]Bristol City vs Wrexham[/COLOR] - [COLOR lime]Sky Sports+[/COLOR] [COLOR orange][gb][/COLOR] [COLOR yellow]Link 1[/COLOR]",
      "myresolve": "sansat@@32@@GB",
      "thumbnail": "https://cdn-icons-png.flaticon.com/512/3524/3524659.png",
      "fanart": "https://www.stadiotardini.it/wp-content/uploads/2016/12/mandrakata.jpg",
      "info": "17-Feb 20:45 | England Championship | Football | Lang: GB"
    },
    {
      "title": "[COLOR cyan][17/02 20:45][/COLOR] [COLOR gold]Bristol City vs Wrexham[/COLOR] - [COLOR lime]Sky Sports+[/COLOR] [COLOR orange][gb][/COLOR] [COLOR yellow]Link 2[/COLOR]",
      "myresolve": "sansat@@32@@GB",
      "thumbnail": "https://cdn-icons-png.flaticon.com/512/3524/3524659.png",
      "fanart": "https://www.stadiotardini.it/wp-content/uploads/2016/12/mandrakata.jpg",
      "info": "17-Feb 20:45 | England Championship | Football | Lang: GB"
    },
    {
      "title": "[COLOR cyan][17/02 21:00][/COLOR] [COLOR gold]Blackpool vs Mansfield Town[/COLOR] - [COLOR lime]Sky Sports Football[/COLOR] [COLOR orange][gb][/COLOR] [COLOR yellow]Link 1[/COLOR]",
      "myresolve": "sansat@@33@@GB",
      "thumbnail": "https://cdn-icons-png.flaticon.com/512/3524/3524659.png",
      "fanart": "https://www.stadiotardini.it/wp-content/uploads/2016/12/mandrakata.jpg",
      "info": "17-Feb 21:00 | England League One | Football | Lang: GB"
    },
    {
      "title": "[COLOR cyan][17/02 21:00][/COLOR] [COLOR gold]Blackpool vs Mansfield Town[/COLOR] - [COLOR lime]Sky Sports Football[/COLOR] [COLOR orange][gb][/COLOR] [COLOR yellow]Link 2[/COLOR]",
      "myresolve": "sansat@@33@@GB",
      "thumbnail": "https://cdn-icons-png.flaticon.com/512/3524/3524659.png",
      "fanart": "https://www.stadiotardini.it/wp-content/uploads/2016/12/mandrakata.jpg",
      "info": "17-Feb 21:00 | England League One | Football | Lang: GB"
    }
  ]
}